simple_ats/__init__.py
simple_ats/ats.py
simple_ats-3.0.0.dist-info/LICENSE
simple_ats-3.0.0.dist-info/METADATA
simple_ats-3.0.0.dist-info/WHEEL
simple_ats-3.0.0.dist-info/entry_points.txt
simple_ats-3.0.0.dist-info/top_level.txt
simple_ats-3.0.0.dist-info/RECORD
