Metadata-Version: 2.1
Name: simple-ats
Version: 3.0.0
Summary: A simple package to return a similarity score between a resume and a job description.
Home-page: https://github.com/Spartan-119/ats_pypi
Author: Abin Varghese
Author-email: abinvarghese90@gmail.com
Classifier: Programming Language :: Python :: 3
Classifier: License :: OSI Approved :: MIT License
Classifier: Operating System :: OS Independent
Requires-Python: >=3.10
License-File: LICENSE
Requires-Dist: spacy
Requires-Dist: sentence-transformers
Requires-Dist: nltk
